drft/__init__.py
drft/authentication.py
drft/filters.py
drft/manage.py
drft/models.py
drft/pagination.py
drft/secrets.py
drft/serializers.py
drft/signing.py
drft/swagger.py
drft/views.py
drft-0.0.0a1.dist-info/entry_points.txt
drft-0.0.0a1.dist-info/LICENSE
drft-0.0.0a1.dist-info/WHEEL
drft-0.0.0a1.dist-info/METADATA
drft-0.0.0a1.dist-info/RECORD
