Metadata-Version: 2.1
Name: drft
Version: 0.0.0a1
Summary: 
License: MIT
Author: Anthony Almarza
Author-email: anthony.almarza@gmail.com
Requires-Python: >=3.8,<4.0
Classifier: Development Status :: 3 - Alpha
Classifier: License :: OSI Approved :: MIT License
Classifier: Natural Language :: English
Classifier: Programming Language :: Python :: 3
Classifier: Programming Language :: Python :: 3 :: Only
Classifier: Programming Language :: Python :: 3.8
Classifier: Programming Language :: Python :: 3.9
Classifier: Topic :: Software Development :: Libraries :: Python Modules
Provides-Extra: yasg
Requires-Dist: Django (>=3.0,<4.0)
Requires-Dist: django-filter (>=2.2.0,<3.0.0)
Requires-Dist: djangorestframework (>=3.11,<4.0)
Requires-Dist: drf-yasg (>=1.17,<2.0); extra == "yasg"
